kaisaglobalapi/__init__.py
kaisaglobalapi/readme.md
kaisaglobalapi/common/KaisaCrypto.py
kaisaglobalapi/common/KaisaFinaData.py
kaisaglobalapi/common/KaisaGateway.py
kaisaglobalapi/common/KaisaHistQuoteData.py
kaisaglobalapi/common/KaisaProtoc.py
kaisaglobalapi/common/KaisaTechData.py
kaisaglobalapi/common/__init__.py
kaisaglobalapi/common/com.py
kaisaglobalapi/common/pub_cls_com.py
kaisaglobalapi/common/utils.py
kaisaglobalapi/common/KCrypto/__init__.py
kaisaglobalapi/common/KCrypto/__init__.pyi
kaisaglobalapi/common/KCrypto/app.py
kaisaglobalapi/common/KCrypto/decryptoapp.py
kaisaglobalapi/common/KCrypto/py.typed
kaisaglobalapi/common/KCrypto/settings.py
kaisaglobalapi/common/KCrypto/Cipher/AES.py
kaisaglobalapi/common/KCrypto/Cipher/AES.pyi
kaisaglobalapi/common/KCrypto/Cipher/ARC2.py
kaisaglobalapi/common/KCrypto/Cipher/ARC2.pyi
kaisaglobalapi/common/KCrypto/Cipher/ARC4.py
kaisaglobalapi/common/KCrypto/Cipher/ARC4.pyi
kaisaglobalapi/common/KCrypto/Cipher/Blowfish.py
kaisaglobalapi/common/KCrypto/Cipher/Blowfish.pyi
kaisaglobalapi/common/KCrypto/Cipher/CAST.py
kaisaglobalapi/common/KCrypto/Cipher/CAST.pyi
kaisaglobalapi/common/KCrypto/Cipher/ChaCha20.py
kaisaglobalapi/common/KCrypto/Cipher/ChaCha20.pyi
kaisaglobalapi/common/KCrypto/Cipher/ChaCha20_Poly1305.py
kaisaglobalapi/common/KCrypto/Cipher/ChaCha20_Poly1305.pyi
kaisaglobalapi/common/KCrypto/Cipher/DES.py
kaisaglobalapi/common/KCrypto/Cipher/DES.pyi
kaisaglobalapi/common/KCrypto/Cipher/DES3.py
kaisaglobalapi/common/KCrypto/Cipher/DES3.pyi
kaisaglobalapi/common/KCrypto/Cipher/PKCS1_OAEP.py
kaisaglobalapi/common/KCrypto/Cipher/PKCS1_OAEP.pyi
kaisaglobalapi/common/KCrypto/Cipher/PKCS1_v1_5.py
kaisaglobalapi/common/KCrypto/Cipher/PKCS1_v1_5.pyi
kaisaglobalapi/common/KCrypto/Cipher/Salsa20.py
kaisaglobalapi/common/KCrypto/Cipher/Salsa20.pyi
kaisaglobalapi/common/KCrypto/Cipher/_ARC4.pyd
kaisaglobalapi/common/KCrypto/Cipher/_EKSBlowfish.py
kaisaglobalapi/common/KCrypto/Cipher/_EKSBlowfish.pyi
kaisaglobalapi-1.2.3.3.dist-info/METADATA
kaisaglobalapi-1.2.3.3.dist-info/WHEEL
kaisaglobalapi-1.2.3.3.dist-info/top_level.txt
kaisaglobalapi-1.2.3.3.dist-info/RECORD
